dialogus/__init__.py
dialogus/asynchronous/__init__.py
dialogus/asynchronous/manager.py
dialogus/messages/__init__.py
dialogus/messages/message.py
dialogus/observers/observer.py
dialogus/processors/composite.py
dialogus/processors/processor.py
dialogus/processors/topology.py
dialogus/utils/__init__.py
dialogus/utils/base_object.py
dialogus/utils/exceptions.py
dialogus/utils/logging.py
dialogus/utils/utils.py
dialogus-0.1.2.dist-info/licenses/LICENSE
dialogus-0.1.2.dist-info/METADATA
dialogus-0.1.2.dist-info/WHEEL
dialogus-0.1.2.dist-info/top_level.txt
dialogus-0.1.2.dist-info/RECORD
