Metadata-Version: 2.4
Name: dialogus
Version: 0.1.2
Summary: A compositional framework for dialogue systems.
Author-email: Comprimus Technologies <contact@comprimus.com>
License-Expression: BSD-3-Clause
Project-URL: Source, https://github.com/comprimus/dialogus
Project-URL: Website, https://comprimus.com
Keywords: ai,chatbots
Classifier: Development Status :: 3 - Alpha
Classifier: Intended Audience :: Developers
Classifier: Programming Language :: Python :: 3
Classifier: Topic :: Scientific/Engineering :: Artificial Intelligence
Requires-Python: >=3.13
License-File: LICENSE
Requires-Dist: loguru>=0.7.3
Dynamic: license-file
